<annotation><folder>Unspecified</folder><filename>1653659077964.jpeg</filename><path>Unspecified</path><source><database>Unknown</database></source><size><width>640</width><height>640</height><depth>3</depth></size><segmented>0</segmented><object><name>ANT</name><pose>Unspecified</pose><truncated>0</truncated><difficult>0</difficult><segmentation><x>235.046875</x><y>120.5</y></segmentation><segmentation><x>239.046875</x><y>114.5</y></segmentation><segmentation><x>269.046875</x><y>149</y></segmentation><segmentation><x>297.046875</x><y>188.5</y></segmentation><segmentation><x>310.046875</x><y>222.5</y></segmentation><segmentation><x>319.046875</x><y>259.5</y></segmentation><segmentation><x>304.046875</x><y>261.5</y></segmentation><segmentation><x>299.046875</x><y>226.5</y></segmentation><segmentation><x>286.046875</x><y>192.5</y></segmentation><segmentation><x>261.046875</x><y>154.5</y></segmentation></object><object><name>ANT</name><pose>Unspecified</pose><truncated>0</truncated><difficult>0</difficult><segmentation><x>466.046875</x><y>144.5</y></segmentation><segmentation><x>470.046875</x><y>146.5</y></segmentation><segmentation><x>435.046875</x><y>178.5</y></segmentation><segmentation><x>396.046875</x><y>205.5</y></segmentation><segmentation><x>363.046875</x><y>235.5</y></segmentation><segmentation><x>342.046875</x><y>268.5</y></segmentation><segmentation><x>329.046875</x><y>261.5</y></segmentation><segmentation><x>355.046875</x><y>224.5</y></segmentation><segmentation><x>389.046875</x><y>198.5</y></segmentation><segmentation><x>430.046875</x><y>172.5</y></segmentation></object><object><name>HEAD</name><pose>Unspecified</pose><truncated>0</truncated><difficult>0</difficult><segmentation><x>298.046875</x><y>261.5</y></segmentation><segmentation><x>325.046875</x><y>255.5</y></segmentation><segmentation><x>347.046875</x><y>262.5</y></segmentation><segmentation><x>349.046875</x><y>278.5</y></segmentation><segmentation><x>344.046875</x><y>299.5</y></segmentation><segmentation><x>323.046875</x><y>303.5</y></segmentation><segmentation><x>297.046875</x><y>299.5</y></segmentation><segmentation><x>296.046875</x><y>278.5</y></segmentation></object><object><name>URS</name><pose>Unspecified</pose><truncated>0</truncated><difficult>0</difficult><segmentation><x>314.046875</x><y>299.5</y></segmentation><segmentation><x>328.046875</x><y>301.5</y></segmentation><segmentation><x>326.046875</x><y>354.5</y></segmentation><segmentation><x>314.046875</x><y>356.5</y></segmentation></object><object><name>CAUDA</name><pose>Unspecified</pose><truncated>0</truncated><difficult>0</difficult><segmentation><x>325.046875</x><y>417.5</y></segmentation><segmentation><x>350.046875</x><y>417.5</y></segmentation><segmentation><x>350.046875</x><y>451.5</y></segmentation><segmentation><x>336.046875</x><y>455.5</y></segmentation></object><object><name>SIPH</name><pose>Unspecified</pose><truncated>0</truncated><difficult>0</difficult><segmentation><x>296.046875</x><y>407.5</y></segmentation><segmentation><x>314.046875</x><y>406.5</y></segmentation><segmentation><x>315.046875</x><y>430.5</y></segmentation><segmentation><x>314.046875</x><y>450.5</y></segmentation><segmentation><x>302.046875</x><y>447.5</y></segmentation><segmentation><x>300.046875</x><y>430.5</y></segmentation></object><object><name>SIPH</name><pose>Unspecified</pose><truncated>0</truncated><difficult>0</difficult><segmentation><x>362.046875</x><y>389.5</y></segmentation><segmentation><x>410.046875</x><y>404.5</y></segmentation><segmentation><x>404.046875</x><y>416.5</y></segmentation><segmentation><x>362.046875</x><y>407.5</y></segmentation></object></annotation>