<annotation><folder>Unspecified</folder><filename>1652276222558.jpeg</filename><path>Unspecified</path><source><database>Unknown</database></source><size><width>640</width><height>640</height><depth>3</depth></size><segmented>0</segmented><object><name>CAUDA</name><pose>Unspecified</pose><truncated>0</truncated><difficult>0</difficult><segmentation><x>265.5</x><y>453.28125</y></segmentation><segmentation><x>288.5</x><y>452.28125</y></segmentation><segmentation><x>289.5</x><y>485.28125</y></segmentation><segmentation><x>290.5</x><y>503.28125</y></segmentation><segmentation><x>269.5</x><y>515.28125</y></segmentation><segmentation><x>270.5</x><y>486.28125</y></segmentation></object><object><name>SIPH</name><pose>Unspecified</pose><truncated>0</truncated><difficult>0</difficult><segmentation><x>167.5</x><y>426.28125</y></segmentation><segmentation><x>183.5</x><y>415.28125</y></segmentation><segmentation><x>207.5</x><y>398.28125</y></segmentation><segmentation><x>216.5</x><y>413.28125</y></segmentation><segmentation><x>192.5</x><y>424.28125</y></segmentation><segmentation><x>176.5</x><y>438.28125</y></segmentation></object><object><name>SIPH</name><pose>Unspecified</pose><truncated>0</truncated><difficult>0</difficult><segmentation><x>278.5</x><y>418.28125</y></segmentation><segmentation><x>303.5</x><y>419.28125</y></segmentation><segmentation><x>305.5</x><y>446.28125</y></segmentation><segmentation><x>305.5</x><y>464.28125</y></segmentation><segmentation><x>293.5</x><y>473.28125</y></segmentation><segmentation><x>291.5</x><y>450.28125</y></segmentation></object><object><name>HEAD</name><pose>Unspecified</pose><truncated>0</truncated><difficult>0</difficult><segmentation><x>287.5</x><y>185.28125</y></segmentation><segmentation><x>306.5</x><y>189.28125</y></segmentation><segmentation><x>315.5</x><y>182.28125</y></segmentation><segmentation><x>331.5</x><y>196.28125</y></segmentation><segmentation><x>335.5</x><y>221.28125</y></segmentation><segmentation><x>332.5</x><y>233.28125</y></segmentation><segmentation><x>313.5</x><y>243.28125</y></segmentation><segmentation><x>288.5</x><y>244.28125</y></segmentation><segmentation><x>269.5</x><y>228.28125</y></segmentation><segmentation><x>272.5</x><y>206.28125</y></segmentation></object><object><name>URS</name><pose>Unspecified</pose><truncated>0</truncated><difficult>0</difficult><segmentation><x>315.5</x><y>270.28125</y></segmentation><segmentation><x>329.5</x><y>272.28125</y></segmentation><segmentation><x>330.5</x><y>294.28125</y></segmentation><segmentation><x>323.5</x><y>319.28125</y></segmentation></object><object><name>ANT</name><pose>Unspecified</pose><truncated>0</truncated><difficult>0</difficult><segmentation><x>11.5</x><y>129.28125</y></segmentation><segmentation><x>99.5</x><y>144.28125</y></segmentation><segmentation><x>157</x><y>148.78125</y></segmentation><segmentation><x>230.5</x><y>151.28125</y></segmentation><segmentation><x>296.5</x><y>166.28125</y></segmentation><segmentation><x>288</x><y>181.28125</y></segmentation><segmentation><x>275.5</x><y>187.28125</y></segmentation><segmentation><x>262.5</x><y>176.28125</y></segmentation><segmentation><x>166.5</x><y>164.28125</y></segmentation><segmentation><x>73.5</x><y>155.28125</y></segmentation><segmentation><x>17.5</x><y>147.28125</y></segmentation></object><object><name>ANT</name><pose>Unspecified</pose><truncated>0</truncated><difficult>0</difficult><segmentation><x>388.5</x><y>155.28125</y></segmentation><segmentation><x>428</x><y>159.78125</y></segmentation><segmentation><x>467.5</x><y>164.28125</y></segmentation><segmentation><x>503.5</x><y>176.28125</y></segmentation><segmentation><x>527.5</x><y>185.28125</y></segmentation><segmentation><x>554.5</x><y>200.78125</y></segmentation><segmentation><x>570.5</x><y>212.28125</y></segmentation><segmentation><x>480.5</x><y>186.28125</y></segmentation><segmentation><x>436.5</x><y>176.28125</y></segmentation><segmentation><x>359.5</x><y>175.28125</y></segmentation><segmentation><x>321.5</x><y>190.28125</y></segmentation><segmentation><x>319.5</x><y>168.28125</y></segmentation><segmentation><x>345.5</x><y>163.28125</y></segmentation><segmentation><x>370.5</x><y>157.28125</y></segmentation></object></annotation>