<annotation><folder>Unspecified</folder><filename>1652793881278.jpeg</filename><path>Unspecified</path><source><database>Unknown</database></source><size><width>640</width><height>640</height><depth>3</depth></size><segmented>0</segmented><object><name>SIPH</name><pose>Unspecified</pose><truncated>0</truncated><difficult>0</difficult><segmentation><x>260.39274439251267</x><y>257.27709306974174</y></segmentation><segmentation><x>315.73112342666514</x><y>275.5585218578085</y></segmentation><segmentation><x>297.6967409735722</x><y>306.19226739456906</y></segmentation><segmentation><x>279.6623585204793</x><y>336.8260129313296</y></segmentation><segmentation><x>251.00498366350973</x><y>363.5070171085101</y></segmentation><segmentation><x>233.71174021533847</x><y>399.08168934474816</y></segmentation><segmentation><x>200.11343865889143</x><y>384.75300191626343</y></segmentation><segmentation><x>216.91258943711495</x><y>360.04836841887595</y></segmentation><segmentation><x>235.68811089512946</x><y>325.955974192481</y></segmentation><segmentation><x>252.98135434330072</x><y>282.96991190702676</y></segmentation></object><object><name>SIPH</name><pose>Unspecified</pose><truncated>0</truncated><difficult>0</difficult><segmentation><x>458.52390504156494</x><y>432.1858982312475</y></segmentation><segmentation><x>467.9116657705722</x><y>446.26753932475845</y></segmentation><segmentation><x>478.78170450942264</x><y>462.32555109806026</y></segmentation><segmentation><x>487.6753725684822</x><y>472.4544508319892</y></segmentation><segmentation><x>498.05131863738495</x><y>484.55972124570906</y></segmentation><segmentation><x>468.6528047754938</x><y>501.3588720239326</y></segmentation><segmentation><x>439.25429091360263</x><y>518.1580228021561</y></segmentation><segmentation><x>418.00830610584933</x><y>529.5221542109545</y></segmentation><segmentation><x>381.9395411996635</x><y>560.6499924176627</y></segmentation><segmentation><x>361.187649061858</x><y>538.4158222700139</y></segmentation><segmentation><x>382.4336338696113</x><y>516.9227911272868</y></segmentation><segmentation><x>403.6796186773646</x><y>495.4297599845596</y></segmentation><segmentation><x>429.3724375146476</x><y>468.25466313743334</y></segmentation></object><object><name>CAUDA</name><pose>Unspecified</pose><truncated>0</truncated><difficult>0</difficult><segmentation><x>254.95772502309177</x><y>505.80570605346236</y></segmentation><segmentation><x>269.28641245157655</x><y>528.5339688710588</y></segmentation><segmentation><x>282.13282187021804</x><y>543.8508416394392</y></segmentation><segmentation><x>313.7547527468741</x><y>560.1558997477149</y></segmentation><segmentation><x>275.95666349587117</x><y>559.908853412741</y></segmentation><segmentation><x>238.15857424486825</x><y>559.6618070777672</y></segmentation><segmentation><x>244.08768628424127</x><y>531.9926175606931</y></segmentation></object></annotation>